Compiled from "BridgeMethods.java"
public class ru.tisov.denis.puzzlers.BridgeMethods {
  public ru.tisov.denis.puzzlers.BridgeMethods();
    Code:
       0: aload_0
       1: invokespecial #1                  // Method java/lang/Object."<init>":()V
       4: return

  public static void main(java.lang.String[]);
    Code:
       0: new           #2                  // class ru/tisov/denis/puzzlers/BridgeMethods
       3: dup
       4: invokespecial #3                  // Method "<init>":()V
       7: invokespecial #4                  // Method go:()V
      10: return

  private void go();
    Code:
       0: new           #5                  // class ru/tisov/denis/puzzlers/BridgeMethods$MyNode
       3: dup
       4: aload_0
       5: iconst_5
       6: invokestatic  #6                  // Method java/lang/Integer.valueOf:(I)Ljava/lang/Integer;
       9: invokespecial #7                  // Method ru/tisov/denis/puzzlers/BridgeMethods$MyNode."<init>":(Lru/tisov/denis/puzzlers/BridgeMethods;Ljava/lang/Integer;)V
      12: astore_1
      13: aload_1
      14: astore_2
      15: aload_2
      16: ldc           #8                  // String String
      18: invokevirtual #9                  // Method ru/tisov/denis/puzzlers/BridgeMethods$Node.setData:(Ljava/lang/Object;)V
      21: aload_1
      22: getfield      #10                 // Field ru/tisov/denis/puzzlers/BridgeMethods$MyNode.data:Ljava/lang/Object;
      25: checkcast     #11                 // class java/lang/Integer
      28: astore_3
      29: getstatic     #12                 // Field java/lang/System.out:Ljava/io/PrintStream;
      32: aload_3
      33: invokevirtual #13                 // Method java/io/PrintStream.println:(Ljava/lang/Object;)V
      36: return
}
